DailyTrends/__init__.py
DailyTrends/collect.py
DailyTrends/request.py
DailyTrends/rescale.py
DailyTrends/test_rescaler.py
DailyTrends-5.0.dist-info/LICENSE
DailyTrends-5.0.dist-info/METADATA
DailyTrends-5.0.dist-info/WHEEL
DailyTrends-5.0.dist-info/top_level.txt
DailyTrends-5.0.dist-info/RECORD
