Metadata-Version: 2.1
Name: DailyTrends
Version: 5.0
Summary: A package to receive full-range daily Google Trends data
Home-page: https://github.com/le0x99/DailyTrends/
Author: Leonard Vorbeck
Author-email: leomxyy@googlemail.com
License: UNKNOWN
Platform: UNKNOWN
Classifier: Programming Language :: Python :: 3.7
Classifier: Programming Language :: Python :: 3.6
Classifier: Programming Language :: Python :: 3.5
Classifier: Programming Language :: Python :: 3.8
Classifier: Programming Language :: Python :: 3.9
Classifier: License :: OSI Approved :: GNU General Public License v3 (GPLv3)
License-File: LICENSE
Requires-Dist: pandas (>=0.24.2)
Requires-Dist: numpy (>=1.16.4)
Requires-Dist: requests (>=2.22.0)
Requires-Dist: tqdm (>=4.35.0)
